webStash/__init__.py
webStash/cacher.py
webStash/config.py
webStash/exceptions.py
webStash/getter.py
webStash/webData.py
webStash/webMine.py
webStash/webStash.py
webStash-0.0.11.dist-info/METADATA
webStash-0.0.11.dist-info/RECORD
webStash-0.0.11.dist-info/WHEEL
webStash-0.0.11.dist-info/top_level.txt
