Metadata-Version: 2.1
Name: webStash
Version: 0.0.11
Summary: Stashing the html for later
Home-page: https://github.com/alexsieusahai/webStash
Author: Alex Sieusahai
Author-email: alexsieu14@gmail.com
License: MIT License
Platform: UNKNOWN
